paper_search_mcp/__init__.py
paper_search_mcp/paper.py
paper_search_mcp/server.py
paper_search_mcp/academic_platforms/__init__.py
paper_search_mcp/academic_platforms/arxiv.py
paper_search_mcp/academic_platforms/biorxiv.py
paper_search_mcp/academic_platforms/google_scholar.py
paper_search_mcp/academic_platforms/hub.py
paper_search_mcp/academic_platforms/medrxiv.py
paper_search_mcp/academic_platforms/pubmed.py
paper_search_mcp-0.1.3.dist-info/METADATA
paper_search_mcp-0.1.3.dist-info/WHEEL
paper_search_mcp-0.1.3.dist-info/licenses/LICENSE
paper_search_mcp-0.1.3.dist-info/RECORD
