Metadata-Version: 2.4
Name: paper-search-mcp
Version: 0.1.3
Summary: A MCP server for searching and downloading academic papers from multiple sources.
Author-email: "P.S Zhang" <pengsongzhang96@gmail.com>
License-File: LICENSE
Requires-Python: >=3.10
Requires-Dist: beautifulsoup4>=4.12.0
Requires-Dist: fastmcp
Requires-Dist: feedparser
Requires-Dist: lxml>=4.9.0
Requires-Dist: mcp[cli]>=1.6.0
Requires-Dist: pypdf2>=3.0.0
Requires-Dist: requests
